MANIFEST.in
README.md
setup.cfg
setup.py
bin/qw-client
bin/qw-manager
qw/__init__.py
qw/client.py
qw/exception.py
qw/logging_setup.py
qw/manager.py
qw/utils.py
qw/worker.py
qw.egg-info/PKG-INFO
qw.egg-info/SOURCES.txt
qw.egg-info/dependency_links.txt
qw.egg-info/requires.txt
qw.egg-info/top_level.txt