Metadata-Version: 1.1
Name: qw
Version: 0.1.1
Summary: Python Distributed Redis Queue Workers
Home-page: https://github.com/brettlangdon/qw
Author: Brett Langdon
Author-email: brett@blangdon.com
License: MIT
Platform: UNKNOWN
Classifier: Intended Audience :: Developers
Classifier: Programming Language :: Python
Classifier: Programming Language :: Python :: 2.6
Classifier: Programming Language :: Python :: 2.7
Classifier: License :: OSI Approved :: MIT License
Classifier: Topic :: Utilities
